medyator/__init__.py
medyator/errors.py
medyator/medyator.py
medyator/request_handler.py
medyator/sender.py
medyator/contracts/__init__.py
medyator/contracts/request.py
medyator/contracts/service_provider.py
medyator/kink/__init__.py
medyator/kink/kink_service_provider.py
medyator/wrappers/__init__.py
medyator/wrappers/request_handler_wrapper.py
medyator-0.4.0.dist-info/licenses/LICENSE
medyator-0.4.0.dist-info/METADATA
medyator-0.4.0.dist-info/WHEEL
medyator-0.4.0.dist-info/top_level.txt
medyator-0.4.0.dist-info/RECORD
