Metadata-Version: 2.4
Name: Medyator
Version: 0.4.0
Summary: A command and query mediator for Python.
Home-page: https://github.com/misdirection/medyator
Author: Misdirection
Author-email: misdirection@live.de
Classifier: Programming Language :: Python :: 3
Classifier: License :: OSI Approved :: MIT License
Classifier: Operating System :: OS Independent
Requires-Python: >=3.8
License-File: LICENSE
Requires-Dist: kink
Dynamic: author
Dynamic: author-email
Dynamic: classifier
Dynamic: description
Dynamic: description-content-type
Dynamic: home-page
Dynamic: license-file
Dynamic: requires-dist
Dynamic: requires-python
Dynamic: summary
